{
    "enabled": true,
    "tabName": "Stats",
    "column": "statistics_status",
    "columnName": "Report status",
    "skipped_status": "Skipped",
    "rules": {
        "Automated": [
            {
                "custom_automation_status": "Automated",
                "custom_status": "Actual"
            }
        ],
        "Need update": [
            {
                "custom_automation_status": "Need update",
                "custom_status": "Actual"
            }
        ],
        "Can be automated": [
            {
                "custom_automation_status": "Not automated",
                "custom_status": "Actual"
            }
        ],
        "Not ready for automation": [
            {
                "custom_status": "Draft"
            },
            {
                "custom_status": "Need update"
            }
        ]
    }
}